setup.py
whisker/__init__.py
whisker/api.py
whisker/callback.py
whisker/constants.py
whisker/convenience.py
whisker/debug_qt.py
whisker/exceptions.py
whisker/qt.py
whisker/qtclient.py
whisker/random.py
whisker/rawsocketclient.py
whisker/socket.py
whisker/sqlalchemy.py
whisker/test_rawsockets.py
whisker/test_twisted.py
whisker/twistedclient.py
whisker/version.py
whisker.egg-info/PKG-INFO
whisker.egg-info/SOURCES.txt
whisker.egg-info/dependency_links.txt
whisker.egg-info/entry_points.txt
whisker.egg-info/requires.txt
whisker.egg-info/top_level.txt