Metadata-Version: 1.1
Name: whisker
Version: 1.0.4
Summary: Whisker Python client library
Home-page: http://www.whiskercontrol.com/
Author: Rudolf Cardinal
Author-email: rudolf@pobox.com
License: Apache License 2.0
Keywords: whisker research control
Platform: UNKNOWN
Classifier: Development Status :: 3 - Alpha
Classifier: Intended Audience :: Science/Research
Classifier: License :: OSI Approved :: Apache Software License
Classifier: Natural Language :: English
Classifier: Operating System :: OS Independent
Classifier: Programming Language :: Python :: 3
Classifier: Programming Language :: Python :: 3.2
Classifier: Programming Language :: Python :: 3.3
Classifier: Programming Language :: Python :: 3.4
Classifier: Programming Language :: Python :: 3.5
Classifier: Programming Language :: Python :: 3 :: Only
Classifier: Topic :: System :: Hardware
Classifier: Topic :: System :: Networking
